static_scenario_generator/__init__.py
static_scenario_generator/config/__init__.py
static_scenario_generator/config/config.yaml
static_scenario_generator/geo_static_scenario_generator/__init__.py
static_scenario_generator/geo_static_scenario_generator/config/__init__.py
static_scenario_generator/geo_static_scenario_generator/config/config.yaml
static_scenario_generator/geo_static_scenario_generator/geo_scenarios.py
static_scenario_generator/resource_manager/__init__.py
static_scenario_generator/resource_manager/data_manager.py
static_scenario_generator/scenarios.py
static_scenario_generator-1.1.1.dist-info/LICENSE
static_scenario_generator-1.1.1.dist-info/METADATA
static_scenario_generator-1.1.1.dist-info/WHEEL
static_scenario_generator-1.1.1.dist-info/RECORD
