Metadata-Version: 2.1
Name: static_scenario_generator
Version: 1.1.1
Summary: Generation of user defined scenarios for the GOBLIN model
License: MIT
Author: Colm Duffy
Requires-Python: >=3.9,<4.0
Classifier: License :: OSI Approved :: MIT License
Classifier: Programming Language :: Python :: 3
Classifier: Programming Language :: Python :: 3.9
Classifier: Programming Language :: Python :: 3.10
Classifier: Programming Language :: Python :: 3.11
Classifier: Programming Language :: Python :: 3.12
Requires-Dist: catchment_data_api (>=0.1.0,<0.2.0)
Requires-Dist: numpy (>=1.25.0,<2.0.0)
Requires-Dist: pandas (==2.1.4)
Requires-Dist: pyyaml (>=6.0.1,<7.0.0)
